projectify/__init__.py
projectify/core.py
projectify/models/__init__.py
projectify/models/base_files.py
projectify/models/folders.py
projectify/models/ide_files.py
projectify/modules/__init__.py
projectify/modules/dependencies.py
projectify/modules/environment.py
projectify/modules/git_repository.py
projectify/modules/header.py
projectify/modules/ide_configuration.py
projectify/modules/project_structure.py
projectify/modules/setup_project.py
projectify/scripts/__init__.py
projectify-0.1.11.dist-info/LICENSE
projectify-0.1.11.dist-info/METADATA
projectify-0.1.11.dist-info/WHEEL
projectify-0.1.11.dist-info/entry_points.txt
projectify-0.1.11.dist-info/top_level.txt
projectify-0.1.11.dist-info/RECORD
