Metadata-Version: 2.1
Name: projectify
Version: 0.1.11
Summary: A simple tool to create a Python project structure
Author: CyberIngeniero
Author-email: CyberIngeniero <npinoa.ai@gmail.com>
Project-URL: Repository, https://github.com/CyberIngeniero/projectify
Project-URL: Documentation, https://github.com/CyberIngeniero/projectify
Keywords: project,structure,python
Classifier: Development Status :: 4 - Beta
Classifier: Environment :: Console
Classifier: Intended Audience :: Developers
Classifier: Operating System :: OS Independent
Classifier: License :: OSI Approved :: MIT License
Classifier: Programming Language :: Python
Classifier: Programming Language :: Python :: 3.8
Classifier: Programming Language :: Python :: 3.9
Classifier: Programming Language :: Python :: 3.10
Classifier: Programming Language :: Python :: 3.11
Classifier: Programming Language :: Python :: 3.12
Classifier: Programming Language :: Python :: 3.13
Classifier: Programming Language :: Python :: 3 :: Only
Classifier: Topic :: Software Development :: Libraries
Classifier: Topic :: Software Development :: Libraries :: Python Modules
Classifier: Topic :: Utilities
Requires-Python: >=3.8
License-File: LICENSE
Requires-Dist: colorama
Requires-Dist: art
Requires-Dist: packaging
